[
	{
		"name": "crop",
		"id": 1,
		"land": "farm",
		"cost": [
			["pop", 3],
			["timber", 4],
			["metal", 2]
		],
		"sply": [
			["food", 2.5]
		],
		"dmnd": []
	},
	{
		"name": "cattle",
		"id": 2,
		"land": "pasture",
		"cost": [
			["pop", 3],
			["food", 5],
			["metal", 1]
		],
		"sply": [
			["food", 1.5],
			["fiber", 0.5]
		],
		"dmnd": []
	},
	{
		"name": "sheep",
		"id": 3,
		"land": "pasture",
		"cost": [
			["pop", 3],
			["food", 5],
			["metal", 1]
		],
		"sply": [
			["food", 0.5],
			["fiber", 1.5]
		],
		"dmnd": []
	},
	{
		"name": "horses",
		"id": 4,
		"land": "pasture",
		"cost": [
			["pop", 3],
			["food", 3],
			["military", 2],
			["metal", 1]
		],
		"sply": [
			["food", 0.5],
			["military", 1]
		],
		"dmnd": []
	},
	{
		"name": "lumberyard",
		"id": 5,
		"land": "forest",
		"cost": [
			["pop", 5],
			["metal", 2]
		],
		"sply": [
			["timber", 2]
		],
		"dmnd": []
	}
]